AUTHORS.rst
HISTORY.rst
LICENSE.txt
MANIFEST.in
README.md
setup.cfg
setup.py
arksia/__init__.py
arksia/bulk_pipeline_results.py
arksia/bulk_pipeline_run.py
arksia/description_pars_gen.json
arksia/description_pars_source.json
arksia/extract_radial_profile.py
arksia/imager.py
arksia/input_output.py
arksia/parametric_fitter.py
arksia/parametric_forms.py
arksia/pars_gen.json
arksia/pipeline.py
arksia/plot.py
arksia.egg-info/PKG-INFO
arksia.egg-info/SOURCES.txt
arksia.egg-info/dependency_links.txt
arksia.egg-info/requires.txt
arksia.egg-info/top_level.txt
test/tests.py