Metadata-Version: 2.1
Name: arksia
Version: 0.2.1
Summary: arksia, part of the ALMA large program ARKS
Home-page: https://github.com/jeffjennings/arksia
Author: Jeff Jennings, Sebastian Marino
Author-email: jjennings1519@gmail.com
License: LGPLv3
Project-URL: Bug Tracker, https://github.com/jeffjennings/arksia/issues
Keywords: science,astronomy,interferometry
Classifier: Development Status :: 4 - Beta
Classifier: License :: OSI Approved :: GNU Lesser General Public License v3 (LGPLv3)
Classifier: Intended Audience :: Developers
Classifier: Intended Audience :: Science/Research
Classifier: Operating System :: MacOS :: MacOS X
Classifier: Operating System :: POSIX :: Linux
Classifier: Programming Language :: Python :: 3.9
Classifier: Programming Language :: Python :: 3.10
Classifier: Programming Language :: Python :: 3.11
Requires-Python: >=3.9
Provides-Extra: test
Provides-Extra: analysis
License-File: LICENSE.txt
